renovosolutions_instance_service/__init__.py
renovosolutions_instance_service/py.typed
renovosolutions_instance_service/_jsii/__init__.py
renovosolutions_instance_service/_jsii/cdk-library-renovo-instance-service@2.9.120.jsii.tgz
renovosolutions.aws_cdk_renovo_instance_service-2.9.120.dist-info/LICENSE
renovosolutions.aws_cdk_renovo_instance_service-2.9.120.dist-info/METADATA
renovosolutions.aws_cdk_renovo_instance_service-2.9.120.dist-info/WHEEL
renovosolutions.aws_cdk_renovo_instance_service-2.9.120.dist-info/top_level.txt
renovosolutions.aws_cdk_renovo_instance_service-2.9.120.dist-info/RECORD
