Metadata-Version: 2.1
Name: renovosolutions.aws-cdk-renovo-instance-service
Version: 2.9.120
Summary: CDK Construct Library to create instance based services utilizing default configurations for Renovo Solutions.
Home-page: https://github.com/RenovoSolutions/cdk-library-renovo-instance-service.git
Author: Renovo Solutions<webmaster+cdk@renovo1.com>
License: Apache-2.0
Project-URL: Source, https://github.com/RenovoSolutions/cdk-library-renovo-instance-service.git
Platform: UNKNOWN
Classifier: Intended Audience :: Developers
Classifier: Operating System :: OS Independent
Classifier: Programming Language :: JavaScript
Classifier: Programming Language :: Python :: 3 :: Only
Classifier: Programming Language :: Python :: 3.9
Classifier: Programming Language :: Python :: 3.10
Classifier: Programming Language :: Python :: 3.11
Classifier: Typing :: Typed
Classifier: Development Status :: 5 - Production/Stable
Classifier: License :: OSI Approved
Requires-Python: ~=3.9
License-File: LICENSE
Requires-Dist: aws-cdk-lib (<3.0.0,>=2.202.0)
Requires-Dist: constructs (<11.0.0,>=10.0.5)
Requires-Dist: jsii (<2.0.0,>=1.112.0)
Requires-Dist: publication (>=0.0.3)
Requires-Dist: renovosolutions.aws-cdk-aspects-security-group (<3.0.0,>=2.0.43)
Requires-Dist: renovosolutions.aws-cdk-managed-instance-role (<3.0.0,>=2.2.3)
Requires-Dist: typeguard (<4.3.0,>=2.13.3)
